examples/__init__.py
examples/abstraction_example.py
examples/bandit_example.py
examples/belief_mdp_example.py
examples/blank_example.py
examples/brtdp_example.py
examples/feature_example.py
examples/goal_based_options_example.py
examples/grid_from_file_example.py
examples/gym_example.py
examples/lifelong_example.py
examples/markov_game_example.py
examples/new_mdp_example.py
examples/oomdp_example.py
examples/planning_example.py
examples/reproduce_example.py
examples/simple_example.py
examples/srl_example_setup.py
examples/success_example.py
examples/untitled.py
examples/viz_example.py
simple_rl/__init__.py
simple_rl/_version.py
simple_rl/run_experiments.py
simple_rl/abstraction/AbstractValueIterationClass.py
simple_rl/abstraction/AbstractionWrapperClass.py
simple_rl/abstraction/__init__.py
simple_rl/abstraction/hierarchical_planning.py
simple_rl/abstraction/abstr_mdp/MDPHierarchy.py
simple_rl/abstraction/abstr_mdp/RewardFuncClass.py
simple_rl/abstraction/abstr_mdp/TransitionFuncClass.py
simple_rl/abstraction/abstr_mdp/__init__.py
simple_rl/abstraction/abstr_mdp/abstr_mdp_funcs.py
simple_rl/abstraction/action_abs/ActionAbstractionClass.py
simple_rl/abstraction/action_abs/InListPredicateClass.py
simple_rl/abstraction/action_abs/OptionClass.py
simple_rl/abstraction/action_abs/PolicyClass.py
simple_rl/abstraction/action_abs/PolicyFromDictClass.py
simple_rl/abstraction/action_abs/PredicateClass.py
simple_rl/abstraction/action_abs/__init__.py
simple_rl/abstraction/action_abs/aa_helpers.py
simple_rl/abstraction/action_abs/aa_visuals.py
simple_rl/abstraction/features/BucketCodingClass.py
simple_rl/abstraction/features/FeatureWrapperClass.py
simple_rl/abstraction/features/RBFCodingClass.py
simple_rl/abstraction/features/TileCodingClass.py
simple_rl/abstraction/features/__init__.py
simple_rl/abstraction/state_abs/ProbStateAbstractionClass.py
simple_rl/abstraction/state_abs/StateAbstractionClass.py
simple_rl-0.811.dist-info/DESCRIPTION.rst
simple_rl-0.811.dist-info/METADATA
simple_rl-0.811.dist-info/RECORD
simple_rl-0.811.dist-info/WHEEL
simple_rl-0.811.dist-info/metadata.json
simple_rl-0.811.dist-info/top_level.txt
