Metadata-Version: 2.0
Name: simple-rl
Version: 0.811
Summary: A simple framework for experimenting with Reinforcement Learning in Python.
Home-page: https://github.com/david-abel/simple_rl
Author: David Abel
Author-email: david_abel@brown.edu
License: UNKNOWN
Download-URL: https://github.com/david-abel/simple_rl/tarball/0.811
Keywords: Markov Decision Process,MDP,Reinforcement Learning
Platform: UNKNOWN
